{
  "trackers": [
    {
      "id": "t-1",
      "type": "brand",
      "query": "Gojek Indonesia",
      "platforms": [
        "tiktok",
        "instagram",
        "facebook",
        "whatsapp"
      ],
      "createdAt": "2026-07-01T10:00:00.000Z"
    },
    {
      "id": "t-2",
      "type": "hashtag",
      "query": "MediaTrend",
      "platforms": [
        "tiktok",
        "instagram"
      ],
      "createdAt": "2026-07-02T11:30:00.000Z"
    },
    {
      "id": "t-3",
      "type": "brand",
      "query": "Kopi Kenangan",
      "platforms": [
        "instagram",
        "tiktok"
      ],
      "createdAt": "2026-07-05T08:15:00.000Z"
    }
  ],
  "analyzedPosts": [
    {
      "id": "ap-1783955393442",
      "url": "https://www.instagram.com/reel/DUQK7Yek8rU/?igsh=MTR3eW9lMDNwbzk3aQ==",
      "platform": "instagram",
      "title": "Instagram",
      "description": "gimana perasaan seseorang ketika di tinggal menikah",
      "imageUrl": "https://images.unsplash.com/photo-1611162617213-7d7a39e9b1d7?w=300&q=80",
      "sentiment": "neutral",
      "sentimentScore": 0,
      "emotion": "Neutral",
      "engagement": "Medium",
      "hashtags": [
        "#brandmonitoring",
        "#analisissentimen",
        "#sosmed"
      ],
      "analyzedAt": "2026-07-13T15:09:53.442Z"
    }
  ],
  "monitorResults": [
    {
      "platform": "instagram",
      "url": "https://www.instagram.com/share/status/local-619265",
      "author": "Dewi Lestari",
      "title": "Keluhan performa Kopi Kenangan",
      "content": "Kenapa ya Kopi Kenangan belakangan ini agak lelet kalau diakses jam sibuk? Sering dapet pesan error koneksi. #keluhan #kecewa",
      "sentiment": "negative",
      "sentimentScore": -0.74,
      "emotion": "Anger",
      "engagement": "Medium",
      "date": "2026-07-13T17:08:58.291Z",
      "id": "mr-1783962538291-bg",
      "trackerId": "t-3"
    },
    {
      "platform": "tiktok",
      "url": "https://www.tiktok.com/share/status/local-426685",
      "author": "@siti_nurhaliza",
      "title": "Rekomendasi Gojek Indonesia terbaik",
      "content": "Sumpah ini Gojek Indonesia membantu banget buat produktivitas sehari-hari! Pelayanannya cepet dan praktis abis. Sangat direkomendasikan untuk semuanya! #rekomendasi #mantap",
      "sentiment": "positive",
      "sentimentScore": 0.43,
      "emotion": "Joy",
      "engagement": "Medium",
      "date": "2026-07-13T17:08:38.289Z",
      "id": "mr-1783962518289-bg",
      "trackerId": "t-1"
    },
    {
      "platform": "instagram",
      "url": "https://www.instagram.com/share/status/local-653193",
      "author": "@rizky_pratama",
      "title": "Ulasan kritis MediaTrend",
      "content": "Harganya makin naik tapi kualitas pelayanan MediaTrend terasa stagnan. Semoga tim mereka segera melakukan evaluasi menyeluruh. #kecewa",
      "sentiment": "negative",
      "sentimentScore": -0.58,
      "emotion": "Anger",
      "engagement": "Medium",
      "date": "2026-07-13T17:08:18.288Z",
      "id": "mr-1783962498288-bg",
      "trackerId": "t-2"
    },
    {
      "platform": "instagram",
      "url": "https://www.instagram.com/share/status/local-945499",
      "author": "Rina Wulandari",
      "title": "Rekomendasi Kopi Kenangan terbaik",
      "content": "Sumpah ini Kopi Kenangan membantu banget buat produktivitas sehari-hari! Pelayanannya cepet dan praktis abis. Sangat direkomendasikan untuk semuanya! #rekomendasi #mantap",
      "sentiment": "positive",
      "sentimentScore": 0.59,
      "emotion": "Joy",
      "engagement": "High",
      "date": "2026-07-13T17:07:58.288Z",
      "id": "mr-1783962478288-bg",
      "trackerId": "t-3"
    },
    {
      "platform": "instagram",
      "url": "https://www.instagram.com/share/status/local-374616",
      "author": "@andreas_s",
      "title": "Keluhan performa MediaTrend",
      "content": "Kenapa ya MediaTrend belakangan ini agak lelet kalau diakses jam sibuk? Sering dapet pesan error koneksi. #keluhan #kecewa",
      "sentiment": "negative",
      "sentimentScore": -0.73,
      "emotion": "Anger",
      "engagement": "High",
      "date": "2026-07-13T17:07:38.288Z",
      "id": "mr-1783962458288-bg",
      "trackerId": "t-2"
    },
    {
      "platform": "whatsapp",
      "url": "https://www.whatsapp.com/share/status/local-65417",
      "author": "Rina Wulandari",
      "title": "Ulasan kritis Gojek Indonesia",
      "content": "Harganya makin naik tapi kualitas pelayanan Gojek Indonesia terasa stagnan. Semoga tim mereka segera melakukan evaluasi menyeluruh. #kecewa",
      "sentiment": "negative",
      "sentimentScore": -0.62,
      "emotion": "Anger",
      "engagement": "High",
      "date": "2026-07-13T17:07:18.288Z",
      "id": "mr-1783962438288-bg",
      "trackerId": "t-1"
    },
    {
      "platform": "whatsapp",
      "url": "https://www.whatsapp.com/share/status/local-520493",
      "author": "@andreas_s",
      "title": "Review jujur layanan Gojek Indonesia",
      "content": "Keren banget inovasi dari Gojek Indonesia, dapet promo melimpah akhir pekan ini. Adminnya ramah dan penanganannya super cepat! #puas #mantap",
      "sentiment": "positive",
      "sentimentScore": 0.52,
      "emotion": "Joy",
      "engagement": "Medium",
      "date": "2026-07-13T17:06:58.287Z",
      "id": "mr-1783962418287-bg",
      "trackerId": "t-1"
    },
    {
      "platform": "instagram",
      "url": "https://www.instagram.com/share/status/local-143788",
      "author": "@budi_santoso",
      "title": "Review jujur layanan Gojek Indonesia",
      "content": "Keren banget inovasi dari Gojek Indonesia, dapet promo melimpah akhir pekan ini. Adminnya ramah dan penanganannya super cepat! #puas #mantap",
      "sentiment": "positive",
      "sentimentScore": 0.72,
      "emotion": "Joy",
      "engagement": "High",
      "date": "2026-07-13T17:06:38.287Z",
      "id": "mr-1783962398287-bg",
      "trackerId": "t-1"
    },
    {
      "platform": "instagram",
      "url": "https://www.instagram.com/share/status/local-582291",
      "author": "@siti_nurhaliza",
      "title": "Ulasan kritis MediaTrend",
      "content": "Harganya makin naik tapi kualitas pelayanan MediaTrend terasa stagnan. Semoga tim mereka segera melakukan evaluasi menyeluruh. #kecewa",
      "sentiment": "negative",
      "sentimentScore": -0.85,
      "emotion": "Anger",
      "engagement": "High",
      "date": "2026-07-13T17:06:18.286Z",
      "id": "mr-1783962378286-bg",
      "trackerId": "t-2"
    },
    {
      "platform": "tiktok",
      "url": "https://www.tiktok.com/share/status/local-27841",
      "author": "Ahmad Fauzi",
      "title": "Review jujur layanan Gojek Indonesia",
      "content": "Keren banget inovasi dari Gojek Indonesia, dapet promo melimpah akhir pekan ini. Adminnya ramah dan penanganannya super cepat! #puas #mantap",
      "sentiment": "positive",
      "sentimentScore": 0.46,
      "emotion": "Joy",
      "engagement": "Medium",
      "date": "2026-07-13T17:05:58.286Z",
      "id": "mr-1783962358286-bg",
      "trackerId": "t-1"
    },
    {
      "platform": "tiktok",
      "url": "https://www.tiktok.com/share/status/local-991601",
      "author": "Agus Setiawan",
      "title": "Review jujur layanan Gojek Indonesia",
      "content": "Keren banget inovasi dari Gojek Indonesia, dapet promo melimpah akhir pekan ini. Adminnya ramah dan penanganannya super cepat! #puas #mantap",
      "sentiment": "positive",
      "sentimentScore": 0.63,
      "emotion": "Joy",
      "engagement": "Medium",
      "date": "2026-07-13T17:05:38.286Z",
      "id": "mr-1783962338286-bg",
      "trackerId": "t-1"
    },
    {
      "platform": "instagram",
      "url": "https://www.instagram.com/share/status/local-143297",
      "author": "@budi_santoso",
      "title": "Review jujur layanan MediaTrend",
      "content": "Keren banget inovasi dari MediaTrend, dapet promo melimpah akhir pekan ini. Adminnya ramah dan penanganannya super cepat! #puas #mantap",
      "sentiment": "positive",
      "sentimentScore": 0.47,
      "emotion": "Joy",
      "engagement": "High",
      "date": "2026-07-13T17:05:18.285Z",
      "id": "mr-1783962318285-bg",
      "trackerId": "t-2"
    },
    {
      "platform": "facebook",
      "url": "https://www.facebook.com/share/status/local-271961",
      "author": "Rina Wulandari",
      "title": "Diskusi seputar Gojek Indonesia",
      "content": "Ada yang punya pengalaman pakai Gojek Indonesia baru-baru ini? Pengen tau performanya buat penggunaan harian. #diskusi",
      "sentiment": "neutral",
      "sentimentScore": 0.12,
      "emotion": "Neutral",
      "engagement": "Medium",
      "date": "2026-07-13T17:04:58.284Z",
      "id": "mr-1783962298284-bg",
      "trackerId": "t-1"
    },
    {
      "platform": "whatsapp",
      "url": "https://www.whatsapp.com/share/status/local-51854",
      "author": "@andreas_s",
      "title": "Pembaruan sistem Gojek Indonesia",
      "content": "Melihat update terbaru dari aplikasi Gojek Indonesia, sepertinya mereka merombak layout navigasi utamanya. #update",
      "sentiment": "neutral",
      "sentimentScore": -0.09,
      "emotion": "Neutral",
      "engagement": "High",
      "date": "2026-07-13T17:04:38.282Z",
      "id": "mr-1783962278282-bg",
      "trackerId": "t-1"
    },
    {
      "platform": "tiktok",
      "url": "https://www.tiktok.com/share/status/local-394241",
      "author": "@budi_santoso",
      "title": "Review jujur layanan Kopi Kenangan",
      "content": "Keren banget inovasi dari Kopi Kenangan, dapet promo melimpah akhir pekan ini. Adminnya ramah dan penanganannya super cepat! #puas #mantap",
      "sentiment": "positive",
      "sentimentScore": 0.7,
      "emotion": "Joy",
      "engagement": "High",
      "date": "2026-07-13T17:04:18.282Z",
      "id": "mr-1783962258282-bg",
      "trackerId": "t-3"
    },
    {
      "platform": "instagram",
      "url": "https://www.instagram.com/share/status/local-972077",
      "author": "Dewi Lestari",
      "title": "Pembaruan sistem Kopi Kenangan",
      "content": "Melihat update terbaru dari aplikasi Kopi Kenangan, sepertinya mereka merombak layout navigasi utamanya. #update",
      "sentiment": "neutral",
      "sentimentScore": -0.01,
      "emotion": "Neutral",
      "engagement": "Medium",
      "date": "2026-07-13T17:03:58.281Z",
      "id": "mr-1783962238281-bg",
      "trackerId": "t-3"
    },
    {
      "platform": "tiktok",
      "url": "https://www.tiktok.com/share/status/local-114050",
      "author": "@siti_nurhaliza",
      "title": "Diskusi seputar Kopi Kenangan",
      "content": "Ada yang punya pengalaman pakai Kopi Kenangan baru-baru ini? Pengen tau performanya buat penggunaan harian. #diskusi",
      "sentiment": "neutral",
      "sentimentScore": -0.04,
      "emotion": "Neutral",
      "engagement": "High",
      "date": "2026-07-13T17:03:38.281Z",
      "id": "mr-1783962218281-bg",
      "trackerId": "t-3"
    },
    {
      "platform": "tiktok",
      "url": "https://www.tiktok.com/share/status/local-871186",
      "author": "Agus Setiawan",
      "title": "Review jujur layanan Kopi Kenangan",
      "content": "Keren banget inovasi dari Kopi Kenangan, dapet promo melimpah akhir pekan ini. Adminnya ramah dan penanganannya super cepat! #puas #mantap",
      "sentiment": "positive",
      "sentimentScore": 0.61,
      "emotion": "Joy",
      "engagement": "Medium",
      "date": "2026-07-13T17:03:18.279Z",
      "id": "mr-1783962198279-bg",
      "trackerId": "t-3"
    },
    {
      "platform": "tiktok",
      "url": "https://www.tiktok.com/share/status/local-941191",
      "author": "@andreas_s",
      "title": "Keluhan performa MediaTrend",
      "content": "Kenapa ya MediaTrend belakangan ini agak lelet kalau diakses jam sibuk? Sering dapet pesan error koneksi. #keluhan #kecewa",
      "sentiment": "negative",
      "sentimentScore": -0.43,
      "emotion": "Anger",
      "engagement": "High",
      "date": "2026-07-13T17:02:58.278Z",
      "id": "mr-1783962178278-bg",
      "trackerId": "t-2"
    },
    {
      "platform": "facebook",
      "url": "https://www.facebook.com/share/status/local-930078",
      "author": "Ahmad Fauzi",
      "title": "Pembaruan sistem Gojek Indonesia",
      "content": "Melihat update terbaru dari aplikasi Gojek Indonesia, sepertinya mereka merombak layout navigasi utamanya. #update",
      "sentiment": "neutral",
      "sentimentScore": 0.01,
      "emotion": "Neutral",
      "engagement": "High",
      "date": "2026-07-13T17:02:38.277Z",
      "id": "mr-1783962158277-bg",
      "trackerId": "t-1"
    },
    {
      "platform": "instagram",
      "url": "https://www.instagram.com/share/status/local-696083",
      "author": "@budi_santoso",
      "title": "Rekomendasi Kopi Kenangan terbaik",
      "content": "Sumpah ini Kopi Kenangan membantu banget buat produktivitas sehari-hari! Pelayanannya cepet dan praktis abis. Sangat direkomendasikan untuk semuanya! #rekomendasi #mantap",
      "sentiment": "positive",
      "sentimentScore": 0.51,
      "emotion": "Joy",
      "engagement": "Medium",
      "date": "2026-07-13T17:02:18.277Z",
      "id": "mr-1783962138277-bg",
      "trackerId": "t-3"
    },
    {
      "platform": "instagram",
      "url": "https://www.instagram.com/share/status/local-19902",
      "author": "Rina Wulandari",
      "title": "Review jujur layanan MediaTrend",
      "content": "Keren banget inovasi dari MediaTrend, dapet promo melimpah akhir pekan ini. Adminnya ramah dan penanganannya super cepat! #puas #mantap",
      "sentiment": "positive",
      "sentimentScore": 0.65,
      "emotion": "Joy",
      "engagement": "High",
      "date": "2026-07-13T17:01:58.275Z",
      "id": "mr-1783962118275-bg",
      "trackerId": "t-2"
    },
    {
      "platform": "facebook",
      "url": "https://www.facebook.com/share/status/local-178708",
      "author": "@siti_nurhaliza",
      "title": "Keluhan performa Gojek Indonesia",
      "content": "Kenapa ya Gojek Indonesia belakangan ini agak lelet kalau diakses jam sibuk? Sering dapet pesan error koneksi. #keluhan #kecewa",
      "sentiment": "negative",
      "sentimentScore": -0.47,
      "emotion": "Anger",
      "engagement": "High",
      "date": "2026-07-13T17:01:38.275Z",
      "id": "mr-1783962098275-bg",
      "trackerId": "t-1"
    },
    {
      "platform": "tiktok",
      "url": "https://www.tiktok.com/share/status/local-943307",
      "author": "Dewi Lestari",
      "title": "Rekomendasi Kopi Kenangan terbaik",
      "content": "Sumpah ini Kopi Kenangan membantu banget buat produktivitas sehari-hari! Pelayanannya cepet dan praktis abis. Sangat direkomendasikan untuk semuanya! #rekomendasi #mantap",
      "sentiment": "positive",
      "sentimentScore": 0.48,
      "emotion": "Joy",
      "engagement": "High",
      "date": "2026-07-13T17:01:18.273Z",
      "id": "mr-1783962078273-bg",
      "trackerId": "t-3"
    },
    {
      "platform": "facebook",
      "url": "https://www.facebook.com/share/status/local-432755",
      "author": "@siti_nurhaliza",
      "title": "Review jujur layanan Gojek Indonesia",
      "content": "Keren banget inovasi dari Gojek Indonesia, dapet promo melimpah akhir pekan ini. Adminnya ramah dan penanganannya super cepat! #puas #mantap",
      "sentiment": "positive",
      "sentimentScore": 0.77,
      "emotion": "Joy",
      "engagement": "High",
      "date": "2026-07-13T17:00:58.273Z",
      "id": "mr-1783962058273-bg",
      "trackerId": "t-1"
    },
    {
      "platform": "tiktok",
      "url": "https://www.tiktok.com/share/status/local-299315",
      "author": "Dewi Lestari",
      "title": "Keluhan performa MediaTrend",
      "content": "Kenapa ya MediaTrend belakangan ini agak lelet kalau diakses jam sibuk? Sering dapet pesan error koneksi. #keluhan #kecewa",
      "sentiment": "negative",
      "sentimentScore": -0.52,
      "emotion": "Anger",
      "engagement": "Medium",
      "date": "2026-07-13T17:00:38.273Z",
      "id": "mr-1783962038273-bg",
      "trackerId": "t-2"
    },
    {
      "platform": "instagram",
      "url": "https://www.instagram.com/share/status/local-575433",
      "author": "@rizky_pratama",
      "title": "Rekomendasi Kopi Kenangan terbaik",
      "content": "Sumpah ini Kopi Kenangan membantu banget buat produktivitas sehari-hari! Pelayanannya cepet dan praktis abis. Sangat direkomendasikan untuk semuanya! #rekomendasi #mantap",
      "sentiment": "positive",
      "sentimentScore": 0.61,
      "emotion": "Joy",
      "engagement": "High",
      "date": "2026-07-13T17:00:18.272Z",
      "id": "mr-1783962018272-bg",
      "trackerId": "t-3"
    },
    {
      "platform": "tiktok",
      "url": "https://www.tiktok.com/share/status/local-397880",
      "author": "Rina Wulandari",
      "title": "Ulasan kritis Kopi Kenangan",
      "content": "Harganya makin naik tapi kualitas pelayanan Kopi Kenangan terasa stagnan. Semoga tim mereka segera melakukan evaluasi menyeluruh. #kecewa",
      "sentiment": "negative",
      "sentimentScore": -0.75,
      "emotion": "Anger",
      "engagement": "High",
      "date": "2026-07-13T16:59:58.271Z",
      "id": "mr-1783961998271-bg",
      "trackerId": "t-3"
    },
    {
      "platform": "instagram",
      "url": "https://www.instagram.com/share/status/local-729113",
      "author": "@rizky_pratama",
      "title": "Review jujur layanan Gojek Indonesia",
      "content": "Keren banget inovasi dari Gojek Indonesia, dapet promo melimpah akhir pekan ini. Adminnya ramah dan penanganannya super cepat! #puas #mantap",
      "sentiment": "positive",
      "sentimentScore": 0.9,
      "emotion": "Joy",
      "engagement": "Medium",
      "date": "2026-07-13T16:59:38.270Z",
      "id": "mr-1783961978270-bg",
      "trackerId": "t-1"
    },
    {
      "platform": "instagram",
      "url": "https://www.instagram.com/share/status/local-301774",
      "author": "@budi_santoso",
      "title": "Diskusi seputar MediaTrend",
      "content": "Ada yang punya pengalaman pakai MediaTrend baru-baru ini? Pengen tau performanya buat penggunaan harian. #diskusi",
      "sentiment": "neutral",
      "sentimentScore": 0.14,
      "emotion": "Neutral",
      "engagement": "High",
      "date": "2026-07-13T16:59:18.269Z",
      "id": "mr-1783961958269-bg",
      "trackerId": "t-2"
    },
    {
      "platform": "instagram",
      "url": "https://www.instagram.com/share/status/local-870274",
      "author": "Agus Setiawan",
      "title": "Ulasan kritis MediaTrend",
      "content": "Harganya makin naik tapi kualitas pelayanan MediaTrend terasa stagnan. Semoga tim mereka segera melakukan evaluasi menyeluruh. #kecewa",
      "sentiment": "negative",
      "sentimentScore": -0.87,
      "emotion": "Anger",
      "engagement": "High",
      "date": "2026-07-13T16:58:58.268Z",
      "id": "mr-1783961938268-bg",
      "trackerId": "t-2"
    },
    {
      "platform": "instagram",
      "url": "https://www.instagram.com/share/status/local-604054",
      "author": "Agus Setiawan",
      "title": "Pembaruan sistem MediaTrend",
      "content": "Melihat update terbaru dari aplikasi MediaTrend, sepertinya mereka merombak layout navigasi utamanya. #update",
      "sentiment": "neutral",
      "sentimentScore": -0.01,
      "emotion": "Neutral",
      "engagement": "High",
      "date": "2026-07-13T16:58:38.268Z",
      "id": "mr-1783961918268-bg",
      "trackerId": "t-2"
    },
    {
      "platform": "facebook",
      "url": "https://www.facebook.com/share/status/local-58581",
      "author": "Dewi Lestari",
      "title": "Diskusi seputar Gojek Indonesia",
      "content": "Ada yang punya pengalaman pakai Gojek Indonesia baru-baru ini? Pengen tau performanya buat penggunaan harian. #diskusi",
      "sentiment": "neutral",
      "sentimentScore": 0.08,
      "emotion": "Neutral",
      "engagement": "High",
      "date": "2026-07-13T16:58:18.265Z",
      "id": "mr-1783961898265-bg",
      "trackerId": "t-1"
    },
    {
      "platform": "tiktok",
      "url": "https://www.tiktok.com/share/status/local-278325",
      "author": "@siti_nurhaliza",
      "title": "Review jujur layanan MediaTrend",
      "content": "Keren banget inovasi dari MediaTrend, dapet promo melimpah akhir pekan ini. Adminnya ramah dan penanganannya super cepat! #puas #mantap",
      "sentiment": "positive",
      "sentimentScore": 0.75,
      "emotion": "Joy",
      "engagement": "Medium",
      "date": "2026-07-13T16:57:58.265Z",
      "id": "mr-1783961878265-bg",
      "trackerId": "t-2"
    },
    {
      "platform": "instagram",
      "url": "https://www.instagram.com/share/status/local-697885",
      "author": "@rizky_pratama",
      "title": "Diskusi seputar Gojek Indonesia",
      "content": "Ada yang punya pengalaman pakai Gojek Indonesia baru-baru ini? Pengen tau performanya buat penggunaan harian. #diskusi",
      "sentiment": "neutral",
      "sentimentScore": -0.08,
      "emotion": "Neutral",
      "engagement": "Medium",
      "date": "2026-07-13T16:57:38.263Z",
      "id": "mr-1783961858263-bg",
      "trackerId": "t-1"
    },
    {
      "platform": "instagram",
      "url": "https://www.instagram.com/share/status/local-758909",
      "author": "@siti_nurhaliza",
      "title": "Rekomendasi Kopi Kenangan terbaik",
      "content": "Sumpah ini Kopi Kenangan membantu banget buat produktivitas sehari-hari! Pelayanannya cepet dan praktis abis. Sangat direkomendasikan untuk semuanya! #rekomendasi #mantap",
      "sentiment": "positive",
      "sentimentScore": 0.77,
      "emotion": "Joy",
      "engagement": "Medium",
      "date": "2026-07-13T16:57:18.263Z",
      "id": "mr-1783961838263-bg",
      "trackerId": "t-3"
    },
    {
      "platform": "instagram",
      "url": "https://www.instagram.com/share/status/local-912469",
      "author": "@rizky_pratama",
      "title": "Pembaruan sistem Kopi Kenangan",
      "content": "Melihat update terbaru dari aplikasi Kopi Kenangan, sepertinya mereka merombak layout navigasi utamanya. #update",
      "sentiment": "neutral",
      "sentimentScore": 0.02,
      "emotion": "Neutral",
      "engagement": "High",
      "date": "2026-07-13T16:56:58.262Z",
      "id": "mr-1783961818262-bg",
      "trackerId": "t-3"
    },
    {
      "platform": "instagram",
      "url": "https://www.instagram.com/share/status/local-975863",
      "author": "Dewi Lestari",
      "title": "Keluhan performa MediaTrend",
      "content": "Kenapa ya MediaTrend belakangan ini agak lelet kalau diakses jam sibuk? Sering dapet pesan error koneksi. #keluhan #kecewa",
      "sentiment": "negative",
      "sentimentScore": -0.55,
      "emotion": "Anger",
      "engagement": "Medium",
      "date": "2026-07-13T16:56:38.260Z",
      "id": "mr-1783961798260-bg",
      "trackerId": "t-2"
    },
    {
      "platform": "tiktok",
      "url": "https://www.tiktok.com/share/status/local-111537",
      "author": "@rizky_pratama",
      "title": "Review jujur layanan Gojek Indonesia",
      "content": "Keren banget inovasi dari Gojek Indonesia, dapet promo melimpah akhir pekan ini. Adminnya ramah dan penanganannya super cepat! #puas #mantap",
      "sentiment": "positive",
      "sentimentScore": 0.74,
      "emotion": "Joy",
      "engagement": "Medium",
      "date": "2026-07-13T16:56:18.259Z",
      "id": "mr-1783961778259-bg",
      "trackerId": "t-1"
    },
    {
      "platform": "instagram",
      "url": "https://www.instagram.com/share/status/local-984055",
      "author": "@siti_nurhaliza",
      "title": "Diskusi seputar MediaTrend",
      "content": "Ada yang punya pengalaman pakai MediaTrend baru-baru ini? Pengen tau performanya buat penggunaan harian. #diskusi",
      "sentiment": "neutral",
      "sentimentScore": -0.03,
      "emotion": "Neutral",
      "engagement": "High",
      "date": "2026-07-13T16:55:58.260Z",
      "id": "mr-1783961758260-bg",
      "trackerId": "t-2"
    },
    {
      "platform": "tiktok",
      "url": "https://www.tiktok.com/share/status/local-582406",
      "author": "Agus Setiawan",
      "title": "Diskusi seputar Kopi Kenangan",
      "content": "Ada yang punya pengalaman pakai Kopi Kenangan baru-baru ini? Pengen tau performanya buat penggunaan harian. #diskusi",
      "sentiment": "neutral",
      "sentimentScore": 0.06,
      "emotion": "Neutral",
      "engagement": "Medium",
      "date": "2026-07-13T16:55:38.260Z",
      "id": "mr-1783961738260-bg",
      "trackerId": "t-3"
    },
    {
      "platform": "instagram",
      "url": "https://www.instagram.com/share/status/local-681116",
      "author": "Rina Wulandari",
      "title": "Review jujur layanan Kopi Kenangan",
      "content": "Keren banget inovasi dari Kopi Kenangan, dapet promo melimpah akhir pekan ini. Adminnya ramah dan penanganannya super cepat! #puas #mantap",
      "sentiment": "positive",
      "sentimentScore": 0.58,
      "emotion": "Joy",
      "engagement": "High",
      "date": "2026-07-13T16:55:18.259Z",
      "id": "mr-1783961718259-bg",
      "trackerId": "t-3"
    },
    {
      "platform": "instagram",
      "url": "https://www.instagram.com/share/status/local-747754",
      "author": "Dewi Lestari",
      "title": "Rekomendasi MediaTrend terbaik",
      "content": "Sumpah ini MediaTrend membantu banget buat produktivitas sehari-hari! Pelayanannya cepet dan praktis abis. Sangat direkomendasikan untuk semuanya! #rekomendasi #mantap",
      "sentiment": "positive",
      "sentimentScore": 0.54,
      "emotion": "Joy",
      "engagement": "Medium",
      "date": "2026-07-13T16:54:58.258Z",
      "id": "mr-1783961698258-bg",
      "trackerId": "t-2"
    },
    {
      "platform": "instagram",
      "url": "https://www.instagram.com/share/status/local-948704",
      "author": "@budi_santoso",
      "title": "Diskusi seputar Kopi Kenangan",
      "content": "Ada yang punya pengalaman pakai Kopi Kenangan baru-baru ini? Pengen tau performanya buat penggunaan harian. #diskusi",
      "sentiment": "neutral",
      "sentimentScore": 0.02,
      "emotion": "Neutral",
      "engagement": "Medium",
      "date": "2026-07-13T16:54:38.258Z",
      "id": "mr-1783961678258-bg",
      "trackerId": "t-3"
    },
    {
      "platform": "instagram",
      "url": "https://www.instagram.com/share/status/local-20259",
      "author": "Ahmad Fauzi",
      "title": "Rekomendasi MediaTrend terbaik",
      "content": "Sumpah ini MediaTrend membantu banget buat produktivitas sehari-hari! Pelayanannya cepet dan praktis abis. Sangat direkomendasikan untuk semuanya! #rekomendasi #mantap",
      "sentiment": "positive",
      "sentimentScore": 0.53,
      "emotion": "Joy",
      "engagement": "High",
      "date": "2026-07-13T16:54:18.256Z",
      "id": "mr-1783961658256-bg",
      "trackerId": "t-2"
    },
    {
      "platform": "instagram",
      "url": "https://www.instagram.com/share/status/local-614336",
      "author": "@budi_santoso",
      "title": "Keluhan performa Gojek Indonesia",
      "content": "Kenapa ya Gojek Indonesia belakangan ini agak lelet kalau diakses jam sibuk? Sering dapet pesan error koneksi. #keluhan #kecewa",
      "sentiment": "negative",
      "sentimentScore": -0.81,
      "emotion": "Anger",
      "engagement": "High",
      "date": "2026-07-13T16:53:58.256Z",
      "id": "mr-1783961638256-bg",
      "trackerId": "t-1"
    },
    {
      "platform": "instagram",
      "url": "https://www.instagram.com/share/status/local-917339",
      "author": "@budi_santoso",
      "title": "Review jujur layanan Kopi Kenangan",
      "content": "Keren banget inovasi dari Kopi Kenangan, dapet promo melimpah akhir pekan ini. Adminnya ramah dan penanganannya super cepat! #puas #mantap",
      "sentiment": "positive",
      "sentimentScore": 0.42,
      "emotion": "Joy",
      "engagement": "High",
      "date": "2026-07-13T16:53:38.256Z",
      "id": "mr-1783961618256-bg",
      "trackerId": "t-3"
    },
    {
      "platform": "tiktok",
      "url": "https://www.tiktok.com/share/status/local-257287",
      "author": "Agus Setiawan",
      "title": "Review jujur layanan Kopi Kenangan",
      "content": "Keren banget inovasi dari Kopi Kenangan, dapet promo melimpah akhir pekan ini. Adminnya ramah dan penanganannya super cepat! #puas #mantap",
      "sentiment": "positive",
      "sentimentScore": 0.72,
      "emotion": "Joy",
      "engagement": "Medium",
      "date": "2026-07-13T16:53:18.256Z",
      "id": "mr-1783961598256-bg",
      "trackerId": "t-3"
    },
    {
      "platform": "tiktok",
      "url": "https://www.tiktok.com/share/status/local-646032",
      "author": "@andreas_s",
      "title": "Pembaruan sistem Kopi Kenangan",
      "content": "Melihat update terbaru dari aplikasi Kopi Kenangan, sepertinya mereka merombak layout navigasi utamanya. #update",
      "sentiment": "neutral",
      "sentimentScore": 0.03,
      "emotion": "Neutral",
      "engagement": "Medium",
      "date": "2026-07-13T16:52:58.255Z",
      "id": "mr-1783961578255-bg",
      "trackerId": "t-3"
    },
    {
      "platform": "instagram",
      "url": "https://www.instagram.com/share/status/local-400359",
      "author": "@rizky_pratama",
      "title": "Review jujur layanan MediaTrend",
      "content": "Keren banget inovasi dari MediaTrend, dapet promo melimpah akhir pekan ini. Adminnya ramah dan penanganannya super cepat! #puas #mantap",
      "sentiment": "positive",
      "sentimentScore": 0.7,
      "emotion": "Joy",
      "engagement": "High",
      "date": "2026-07-13T16:52:38.253Z",
      "id": "mr-1783961558253-bg",
      "trackerId": "t-2"
    },
    {
      "platform": "instagram",
      "url": "https://www.instagram.com/share/status/local-536140",
      "author": "Dewi Lestari",
      "title": "Review jujur layanan Kopi Kenangan",
      "content": "Keren banget inovasi dari Kopi Kenangan, dapet promo melimpah akhir pekan ini. Adminnya ramah dan penanganannya super cepat! #puas #mantap",
      "sentiment": "positive",
      "sentimentScore": 0.83,
      "emotion": "Joy",
      "engagement": "Medium",
      "date": "2026-07-13T16:52:18.252Z",
      "id": "mr-1783961538252-bg",
      "trackerId": "t-3"
    },
    {
      "platform": "tiktok",
      "url": "https://www.tiktok.com/share/status/local-717565",
      "author": "Dewi Lestari",
      "title": "Diskusi seputar MediaTrend",
      "content": "Ada yang punya pengalaman pakai MediaTrend baru-baru ini? Pengen tau performanya buat penggunaan harian. #diskusi",
      "sentiment": "neutral",
      "sentimentScore": 0.15,
      "emotion": "Neutral",
      "engagement": "Medium",
      "date": "2026-07-13T16:51:58.252Z",
      "id": "mr-1783961518252-bg",
      "trackerId": "t-2"
    },
    {
      "platform": "instagram",
      "url": "https://www.instagram.com/share/status/local-132775",
      "author": "Dewi Lestari",
      "title": "Rekomendasi Kopi Kenangan terbaik",
      "content": "Sumpah ini Kopi Kenangan membantu banget buat produktivitas sehari-hari! Pelayanannya cepet dan praktis abis. Sangat direkomendasikan untuk semuanya! #rekomendasi #mantap",
      "sentiment": "positive",
      "sentimentScore": 0.59,
      "emotion": "Joy",
      "engagement": "High",
      "date": "2026-07-13T16:51:38.250Z",
      "id": "mr-1783961498250-bg",
      "trackerId": "t-3"
    },
    {
      "platform": "instagram",
      "url": "https://www.instagram.com/share/status/local-417297",
      "author": "Agus Setiawan",
      "title": "Review jujur layanan MediaTrend",
      "content": "Keren banget inovasi dari MediaTrend, dapet promo melimpah akhir pekan ini. Adminnya ramah dan penanganannya super cepat! #puas #mantap",
      "sentiment": "positive",
      "sentimentScore": 0.68,
      "emotion": "Joy",
      "engagement": "High",
      "date": "2026-07-13T16:51:18.250Z",
      "id": "mr-1783961478250-bg",
      "trackerId": "t-2"
    },
    {
      "platform": "instagram",
      "url": "https://www.instagram.com/share/status/local-400100",
      "author": "@andreas_s",
      "title": "Review jujur layanan MediaTrend",
      "content": "Keren banget inovasi dari MediaTrend, dapet promo melimpah akhir pekan ini. Adminnya ramah dan penanganannya super cepat! #puas #mantap",
      "sentiment": "positive",
      "sentimentScore": 0.47,
      "emotion": "Joy",
      "engagement": "Medium",
      "date": "2026-07-13T16:50:58.248Z",
      "id": "mr-1783961458248-bg",
      "trackerId": "t-2"
    },
    {
      "platform": "tiktok",
      "url": "https://www.tiktok.com/share/status/local-820704",
      "author": "Ahmad Fauzi",
      "title": "Diskusi seputar Kopi Kenangan",
      "content": "Ada yang punya pengalaman pakai Kopi Kenangan baru-baru ini? Pengen tau performanya buat penggunaan harian. #diskusi",
      "sentiment": "neutral",
      "sentimentScore": 0.02,
      "emotion": "Neutral",
      "engagement": "High",
      "date": "2026-07-13T16:50:38.247Z",
      "id": "mr-1783961438247-bg",
      "trackerId": "t-3"
    },
    {
      "platform": "instagram",
      "url": "https://www.instagram.com/share/status/local-603319",
      "author": "@siti_nurhaliza",
      "title": "Pembaruan sistem MediaTrend",
      "content": "Melihat update terbaru dari aplikasi MediaTrend, sepertinya mereka merombak layout navigasi utamanya. #update",
      "sentiment": "neutral",
      "sentimentScore": -0.09,
      "emotion": "Neutral",
      "engagement": "High",
      "date": "2026-07-13T16:50:18.246Z",
      "id": "mr-1783961418246-bg",
      "trackerId": "t-2"
    },
    {
      "platform": "instagram",
      "url": "https://www.instagram.com/share/status/local-723723",
      "author": "@rizky_pratama",
      "title": "Diskusi seputar Gojek Indonesia",
      "content": "Ada yang punya pengalaman pakai Gojek Indonesia baru-baru ini? Pengen tau performanya buat penggunaan harian. #diskusi",
      "sentiment": "neutral",
      "sentimentScore": -0.02,
      "emotion": "Neutral",
      "engagement": "High",
      "date": "2026-07-13T16:49:58.245Z",
      "id": "mr-1783961398245-bg",
      "trackerId": "t-1"
    },
    {
      "platform": "instagram",
      "url": "https://www.instagram.com/share/status/local-204952",
      "author": "@budi_santoso",
      "title": "Diskusi seputar MediaTrend",
      "content": "Ada yang punya pengalaman pakai MediaTrend baru-baru ini? Pengen tau performanya buat penggunaan harian. #diskusi",
      "sentiment": "neutral",
      "sentimentScore": -0.07,
      "emotion": "Neutral",
      "engagement": "Medium",
      "date": "2026-07-13T16:49:38.245Z",
      "id": "mr-1783961378245-bg",
      "trackerId": "t-2"
    },
    {
      "platform": "instagram",
      "url": "https://www.instagram.com/share/status/local-903565",
      "author": "Agus Setiawan",
      "title": "Rekomendasi Kopi Kenangan terbaik",
      "content": "Sumpah ini Kopi Kenangan membantu banget buat produktivitas sehari-hari! Pelayanannya cepet dan praktis abis. Sangat direkomendasikan untuk semuanya! #rekomendasi #mantap",
      "sentiment": "positive",
      "sentimentScore": 0.89,
      "emotion": "Joy",
      "engagement": "High",
      "date": "2026-07-13T16:49:18.244Z",
      "id": "mr-1783961358244-bg",
      "trackerId": "t-3"
    },
    {
      "platform": "tiktok",
      "url": "https://www.tiktok.com/share/status/local-369167",
      "author": "@rizky_pratama",
      "title": "Rekomendasi Gojek Indonesia terbaik",
      "content": "Sumpah ini Gojek Indonesia membantu banget buat produktivitas sehari-hari! Pelayanannya cepet dan praktis abis. Sangat direkomendasikan untuk semuanya! #rekomendasi #mantap",
      "sentiment": "positive",
      "sentimentScore": 0.76,
      "emotion": "Joy",
      "engagement": "High",
      "date": "2026-07-13T16:48:58.244Z",
      "id": "mr-1783961338244-bg",
      "trackerId": "t-1"
    },
    {
      "platform": "tiktok",
      "url": "https://www.tiktok.com/share/status/local-403187",
      "author": "Dewi Lestari",
      "title": "Rekomendasi Kopi Kenangan terbaik",
      "content": "Sumpah ini Kopi Kenangan membantu banget buat produktivitas sehari-hari! Pelayanannya cepet dan praktis abis. Sangat direkomendasikan untuk semuanya! #rekomendasi #mantap",
      "sentiment": "positive",
      "sentimentScore": 0.44,
      "emotion": "Joy",
      "engagement": "Medium",
      "date": "2026-07-13T16:48:38.244Z",
      "id": "mr-1783961318244-bg",
      "trackerId": "t-3"
    },
    {
      "platform": "facebook",
      "url": "https://www.facebook.com/share/status/local-295779",
      "author": "@andreas_s",
      "title": "Ulasan kritis Gojek Indonesia",
      "content": "Harganya makin naik tapi kualitas pelayanan Gojek Indonesia terasa stagnan. Semoga tim mereka segera melakukan evaluasi menyeluruh. #kecewa",
      "sentiment": "negative",
      "sentimentScore": -0.83,
      "emotion": "Anger",
      "engagement": "High",
      "date": "2026-07-13T16:48:18.243Z",
      "id": "mr-1783961298243-bg",
      "trackerId": "t-1"
    },
    {
      "platform": "tiktok",
      "url": "https://www.tiktok.com/share/status/local-719529",
      "author": "@siti_nurhaliza",
      "title": "Review jujur layanan MediaTrend",
      "content": "Keren banget inovasi dari MediaTrend, dapet promo melimpah akhir pekan ini. Adminnya ramah dan penanganannya super cepat! #puas #mantap",
      "sentiment": "positive",
      "sentimentScore": 0.45,
      "emotion": "Joy",
      "engagement": "Medium",
      "date": "2026-07-13T16:47:58.243Z",
      "id": "mr-1783961278243-bg",
      "trackerId": "t-2"
    },
    {
      "platform": "instagram",
      "url": "https://www.instagram.com/share/status/local-10967",
      "author": "Ahmad Fauzi",
      "title": "Pembaruan sistem MediaTrend",
      "content": "Melihat update terbaru dari aplikasi MediaTrend, sepertinya mereka merombak layout navigasi utamanya. #update",
      "sentiment": "neutral",
      "sentimentScore": -0.06,
      "emotion": "Neutral",
      "engagement": "Medium",
      "date": "2026-07-13T16:47:38.242Z",
      "id": "mr-1783961258242-bg",
      "trackerId": "t-2"
    },
    {
      "platform": "instagram",
      "url": "https://www.instagram.com/share/status/local-288563",
      "author": "@siti_nurhaliza",
      "title": "Rekomendasi Kopi Kenangan terbaik",
      "content": "Sumpah ini Kopi Kenangan membantu banget buat produktivitas sehari-hari! Pelayanannya cepet dan praktis abis. Sangat direkomendasikan untuk semuanya! #rekomendasi #mantap",
      "sentiment": "positive",
      "sentimentScore": 0.46,
      "emotion": "Joy",
      "engagement": "Medium",
      "date": "2026-07-13T16:47:18.242Z",
      "id": "mr-1783961238242-bg",
      "trackerId": "t-3"
    },
    {
      "platform": "whatsapp",
      "url": "https://www.whatsapp.com/share/status/local-383102",
      "author": "Dewi Lestari",
      "title": "Pembaruan sistem Gojek Indonesia",
      "content": "Melihat update terbaru dari aplikasi Gojek Indonesia, sepertinya mereka merombak layout navigasi utamanya. #update",
      "sentiment": "neutral",
      "sentimentScore": 0.07,
      "emotion": "Neutral",
      "engagement": "High",
      "date": "2026-07-13T16:46:58.241Z",
      "id": "mr-1783961218241-bg",
      "trackerId": "t-1"
    },
    {
      "platform": "facebook",
      "url": "https://www.facebook.com/share/status/local-661877",
      "author": "@budi_santoso",
      "title": "Rekomendasi Gojek Indonesia terbaik",
      "content": "Sumpah ini Gojek Indonesia membantu banget buat produktivitas sehari-hari! Pelayanannya cepet dan praktis abis. Sangat direkomendasikan untuk semuanya! #rekomendasi #mantap",
      "sentiment": "positive",
      "sentimentScore": 0.6,
      "emotion": "Joy",
      "engagement": "Medium",
      "date": "2026-07-13T16:46:38.240Z",
      "id": "mr-1783961198240-bg",
      "trackerId": "t-1"
    },
    {
      "platform": "instagram",
      "url": "https://www.instagram.com/share/status/local-292174",
      "author": "@budi_santoso",
      "title": "Pembaruan sistem Kopi Kenangan",
      "content": "Melihat update terbaru dari aplikasi Kopi Kenangan, sepertinya mereka merombak layout navigasi utamanya. #update",
      "sentiment": "neutral",
      "sentimentScore": -0.13,
      "emotion": "Neutral",
      "engagement": "Medium",
      "date": "2026-07-13T16:46:18.239Z",
      "id": "mr-1783961178239-bg",
      "trackerId": "t-3"
    },
    {
      "platform": "instagram",
      "url": "https://www.instagram.com/share/status/local-414216",
      "author": "Agus Setiawan",
      "title": "Review jujur layanan Gojek Indonesia",
      "content": "Keren banget inovasi dari Gojek Indonesia, dapet promo melimpah akhir pekan ini. Adminnya ramah dan penanganannya super cepat! #puas #mantap",
      "sentiment": "positive",
      "sentimentScore": 0.61,
      "emotion": "Joy",
      "engagement": "High",
      "date": "2026-07-13T16:45:58.238Z",
      "id": "mr-1783961158238-bg",
      "trackerId": "t-1"
    },
    {
      "platform": "tiktok",
      "url": "https://www.tiktok.com/share/status/local-772013",
      "author": "@rizky_pratama",
      "title": "Review jujur layanan MediaTrend",
      "content": "Keren banget inovasi dari MediaTrend, dapet promo melimpah akhir pekan ini. Adminnya ramah dan penanganannya super cepat! #puas #mantap",
      "sentiment": "positive",
      "sentimentScore": 0.72,
      "emotion": "Joy",
      "engagement": "High",
      "date": "2026-07-13T16:45:18.514Z",
      "id": "mr-1783961118514-bg",
      "trackerId": "t-2"
    },
    {
      "platform": "instagram",
      "url": "https://www.instagram.com/share/status/local-379594",
      "author": "Rina Wulandari",
      "title": "Ulasan kritis Kopi Kenangan",
      "content": "Harganya makin naik tapi kualitas pelayanan Kopi Kenangan terasa stagnan. Semoga tim mereka segera melakukan evaluasi menyeluruh. #kecewa",
      "sentiment": "negative",
      "sentimentScore": -0.56,
      "emotion": "Anger",
      "engagement": "High",
      "date": "2026-07-13T16:44:58.513Z",
      "id": "mr-1783961098513-bg",
      "trackerId": "t-3"
    },
    {
      "platform": "instagram",
      "url": "https://www.instagram.com/share/status/local-28126",
      "author": "Agus Setiawan",
      "title": "Rekomendasi Kopi Kenangan terbaik",
      "content": "Sumpah ini Kopi Kenangan membantu banget buat produktivitas sehari-hari! Pelayanannya cepet dan praktis abis. Sangat direkomendasikan untuk semuanya! #rekomendasi #mantap",
      "sentiment": "positive",
      "sentimentScore": 0.74,
      "emotion": "Joy",
      "engagement": "High",
      "date": "2026-07-13T16:44:38.513Z",
      "id": "mr-1783961078513-bg",
      "trackerId": "t-3"
    },
    {
      "platform": "instagram",
      "url": "https://www.instagram.com/share/status/local-165020",
      "author": "Ahmad Fauzi",
      "title": "Rekomendasi MediaTrend terbaik",
      "content": "Sumpah ini MediaTrend membantu banget buat produktivitas sehari-hari! Pelayanannya cepet dan praktis abis. Sangat direkomendasikan untuk semuanya! #rekomendasi #mantap",
      "sentiment": "positive",
      "sentimentScore": 0.75,
      "emotion": "Joy",
      "engagement": "Medium",
      "date": "2026-07-13T16:44:18.512Z",
      "id": "mr-1783961058512-bg",
      "trackerId": "t-2"
    },
    {
      "platform": "whatsapp",
      "url": "https://www.whatsapp.com/share/status/local-978611",
      "author": "@budi_santoso",
      "title": "Rekomendasi Gojek Indonesia terbaik",
      "content": "Sumpah ini Gojek Indonesia membantu banget buat produktivitas sehari-hari! Pelayanannya cepet dan praktis abis. Sangat direkomendasikan untuk semuanya! #rekomendasi #mantap",
      "sentiment": "positive",
      "sentimentScore": 0.51,
      "emotion": "Joy",
      "engagement": "Medium",
      "date": "2026-07-13T16:43:58.512Z",
      "id": "mr-1783961038512-bg",
      "trackerId": "t-1"
    },
    {
      "platform": "tiktok",
      "url": "https://www.tiktok.com/share/status/local-295096",
      "author": "Dewi Lestari",
      "title": "Keluhan performa MediaTrend",
      "content": "Kenapa ya MediaTrend belakangan ini agak lelet kalau diakses jam sibuk? Sering dapet pesan error koneksi. #keluhan #kecewa",
      "sentiment": "negative",
      "sentimentScore": -0.75,
      "emotion": "Anger",
      "engagement": "High",
      "date": "2026-07-13T16:43:38.512Z",
      "id": "mr-1783961018512-bg",
      "trackerId": "t-2"
    },
    {
      "platform": "instagram",
      "url": "https://www.instagram.com/share/status/local-292775",
      "author": "@rizky_pratama",
      "title": "Diskusi seputar MediaTrend",
      "content": "Ada yang punya pengalaman pakai MediaTrend baru-baru ini? Pengen tau performanya buat penggunaan harian. #diskusi",
      "sentiment": "neutral",
      "sentimentScore": -0.1,
      "emotion": "Neutral",
      "engagement": "High",
      "date": "2026-07-13T16:43:18.511Z",
      "id": "mr-1783960998511-bg",
      "trackerId": "t-2"
    },
    {
      "platform": "tiktok",
      "url": "https://www.tiktok.com/share/status/local-120990",
      "author": "Ahmad Fauzi",
      "title": "Diskusi seputar Kopi Kenangan",
      "content": "Ada yang punya pengalaman pakai Kopi Kenangan baru-baru ini? Pengen tau performanya buat penggunaan harian. #diskusi",
      "sentiment": "neutral",
      "sentimentScore": -0.15,
      "emotion": "Neutral",
      "engagement": "High",
      "date": "2026-07-13T16:42:58.510Z",
      "id": "mr-1783960978510-bg",
      "trackerId": "t-3"
    },
    {
      "platform": "instagram",
      "url": "https://www.instagram.com/share/status/local-965079",
      "author": "Ahmad Fauzi",
      "title": "Ulasan kritis Kopi Kenangan",
      "content": "Harganya makin naik tapi kualitas pelayanan Kopi Kenangan terasa stagnan. Semoga tim mereka segera melakukan evaluasi menyeluruh. #kecewa",
      "sentiment": "negative",
      "sentimentScore": -0.55,
      "emotion": "Anger",
      "engagement": "Medium",
      "date": "2026-07-13T16:42:38.509Z",
      "id": "mr-1783960958509-bg",
      "trackerId": "t-3"
    },
    {
      "platform": "tiktok",
      "url": "https://www.tiktok.com/share/status/local-620219",
      "author": "Rina Wulandari",
      "title": "Review jujur layanan MediaTrend",
      "content": "Keren banget inovasi dari MediaTrend, dapet promo melimpah akhir pekan ini. Adminnya ramah dan penanganannya super cepat! #puas #mantap",
      "sentiment": "positive",
      "sentimentScore": 0.72,
      "emotion": "Joy",
      "engagement": "High",
      "date": "2026-07-13T16:42:09.583Z",
      "id": "mr-1783960929583-bg",
      "trackerId": "t-2"
    },
    {
      "platform": "instagram",
      "url": "https://www.instagram.com/share/status/local-569430",
      "author": "Dewi Lestari",
      "title": "Rekomendasi Kopi Kenangan terbaik",
      "content": "Sumpah ini Kopi Kenangan membantu banget buat produktivitas sehari-hari! Pelayanannya cepet dan praktis abis. Sangat direkomendasikan untuk semuanya! #rekomendasi #mantap",
      "sentiment": "positive",
      "sentimentScore": 0.79,
      "emotion": "Joy",
      "engagement": "Medium",
      "date": "2026-07-13T16:41:49.581Z",
      "id": "mr-1783960909581-bg",
      "trackerId": "t-3"
    },
    {
      "platform": "tiktok",
      "url": "https://www.tiktok.com/share/status/local-460282",
      "author": "Agus Setiawan",
      "title": "Pembaruan sistem Kopi Kenangan",
      "content": "Melihat update terbaru dari aplikasi Kopi Kenangan, sepertinya mereka merombak layout navigasi utamanya. #update",
      "sentiment": "neutral",
      "sentimentScore": -0.13,
      "emotion": "Neutral",
      "engagement": "Medium",
      "date": "2026-07-13T16:41:29.581Z",
      "id": "mr-1783960889581-bg",
      "trackerId": "t-3"
    },
    {
      "platform": "instagram",
      "url": "https://www.instagram.com/share/status/local-156247",
      "author": "Ahmad Fauzi",
      "title": "Rekomendasi MediaTrend terbaik",
      "content": "Sumpah ini MediaTrend membantu banget buat produktivitas sehari-hari! Pelayanannya cepet dan praktis abis. Sangat direkomendasikan untuk semuanya! #rekomendasi #mantap",
      "sentiment": "positive",
      "sentimentScore": 0.61,
      "emotion": "Joy",
      "engagement": "Medium",
      "date": "2026-07-13T16:41:09.580Z",
      "id": "mr-1783960869580-bg",
      "trackerId": "t-2"
    },
    {
      "platform": "tiktok",
      "url": "https://www.tiktok.com/share/status/local-160404",
      "author": "@rizky_pratama",
      "title": "Keluhan performa MediaTrend",
      "content": "Kenapa ya MediaTrend belakangan ini agak lelet kalau diakses jam sibuk? Sering dapet pesan error koneksi. #keluhan #kecewa",
      "sentiment": "negative",
      "sentimentScore": -0.85,
      "emotion": "Anger",
      "engagement": "Medium",
      "date": "2026-07-13T16:40:49.580Z",
      "id": "mr-1783960849580-bg",
      "trackerId": "t-2"
    },
    {
      "platform": "instagram",
      "url": "https://www.instagram.com/share/status/local-334728",
      "author": "@andreas_s",
      "title": "Rekomendasi Gojek Indonesia terbaik",
      "content": "Sumpah ini Gojek Indonesia membantu banget buat produktivitas sehari-hari! Pelayanannya cepet dan praktis abis. Sangat direkomendasikan untuk semuanya! #rekomendasi #mantap",
      "sentiment": "positive",
      "sentimentScore": 0.78,
      "emotion": "Joy",
      "engagement": "Medium",
      "date": "2026-07-13T16:40:29.579Z",
      "id": "mr-1783960829579-bg",
      "trackerId": "t-1"
    },
    {
      "platform": "tiktok",
      "url": "https://www.tiktok.com/share/status/local-302090",
      "author": "Ahmad Fauzi",
      "title": "Rekomendasi Kopi Kenangan terbaik",
      "content": "Sumpah ini Kopi Kenangan membantu banget buat produktivitas sehari-hari! Pelayanannya cepet dan praktis abis. Sangat direkomendasikan untuk semuanya! #rekomendasi #mantap",
      "sentiment": "positive",
      "sentimentScore": 0.51,
      "emotion": "Joy",
      "engagement": "High",
      "date": "2026-07-13T16:40:09.578Z",
      "id": "mr-1783960809578-bg",
      "trackerId": "t-3"
    },
    {
      "platform": "tiktok",
      "url": "https://www.tiktok.com/share/status/local-349468",
      "author": "Ahmad Fauzi",
      "title": "Ulasan kritis Kopi Kenangan",
      "content": "Harganya makin naik tapi kualitas pelayanan Kopi Kenangan terasa stagnan. Semoga tim mereka segera melakukan evaluasi menyeluruh. #kecewa",
      "sentiment": "negative",
      "sentimentScore": -0.44,
      "emotion": "Anger",
      "engagement": "Medium",
      "date": "2026-07-13T16:39:49.577Z",
      "id": "mr-1783960789577-bg",
      "trackerId": "t-3"
    },
    {
      "platform": "tiktok",
      "url": "https://www.tiktok.com/share/status/local-428312",
      "author": "Rina Wulandari",
      "title": "Rekomendasi Kopi Kenangan terbaik",
      "content": "Sumpah ini Kopi Kenangan membantu banget buat produktivitas sehari-hari! Pelayanannya cepet dan praktis abis. Sangat direkomendasikan untuk semuanya! #rekomendasi #mantap",
      "sentiment": "positive",
      "sentimentScore": 0.88,
      "emotion": "Joy",
      "engagement": "Medium",
      "date": "2026-07-13T16:39:29.576Z",
      "id": "mr-1783960769576-bg",
      "trackerId": "t-3"
    },
    {
      "platform": "tiktok",
      "url": "https://www.tiktok.com/share/status/local-827178",
      "author": "Dewi Lestari",
      "title": "Pembaruan sistem MediaTrend",
      "content": "Melihat update terbaru dari aplikasi MediaTrend, sepertinya mereka merombak layout navigasi utamanya. #update",
      "sentiment": "neutral",
      "sentimentScore": -0.14,
      "emotion": "Neutral",
      "engagement": "High",
      "date": "2026-07-13T16:39:09.576Z",
      "id": "mr-1783960749576-bg",
      "trackerId": "t-2"
    },
    {
      "platform": "instagram",
      "url": "https://www.instagram.com/share/status/local-36278",
      "author": "Agus Setiawan",
      "title": "Review jujur layanan MediaTrend",
      "content": "Keren banget inovasi dari MediaTrend, dapet promo melimpah akhir pekan ini. Adminnya ramah dan penanganannya super cepat! #puas #mantap",
      "sentiment": "positive",
      "sentimentScore": 0.53,
      "emotion": "Joy",
      "engagement": "High",
      "date": "2026-07-13T16:38:33.650Z",
      "id": "mr-1783960713650-bg",
      "trackerId": "t-2"
    },
    {
      "platform": "tiktok",
      "url": "https://www.tiktok.com/share/status/local-208525",
      "author": "@rizky_pratama",
      "title": "Pembaruan sistem MediaTrend",
      "content": "Melihat update terbaru dari aplikasi MediaTrend, sepertinya mereka merombak layout navigasi utamanya. #update",
      "sentiment": "neutral",
      "sentimentScore": -0.11,
      "emotion": "Neutral",
      "engagement": "High",
      "date": "2026-07-13T16:38:13.648Z",
      "id": "mr-1783960693648-bg",
      "trackerId": "t-2"
    },
    {
      "platform": "tiktok",
      "url": "https://www.tiktok.com/share/status/local-507091",
      "author": "Rina Wulandari",
      "title": "Pembaruan sistem Kopi Kenangan",
      "content": "Melihat update terbaru dari aplikasi Kopi Kenangan, sepertinya mereka merombak layout navigasi utamanya. #update",
      "sentiment": "neutral",
      "sentimentScore": 0.12,
      "emotion": "Neutral",
      "engagement": "Medium",
      "date": "2026-07-13T16:37:53.648Z",
      "id": "mr-1783960673648-bg",
      "trackerId": "t-3"
    },
    {
      "platform": "instagram",
      "url": "https://www.instagram.com/share/status/local-191680",
      "author": "Agus Setiawan",
      "title": "Rekomendasi MediaTrend terbaik",
      "content": "Sumpah ini MediaTrend membantu banget buat produktivitas sehari-hari! Pelayanannya cepet dan praktis abis. Sangat direkomendasikan untuk semuanya! #rekomendasi #mantap",
      "sentiment": "positive",
      "sentimentScore": 0.5,
      "emotion": "Joy",
      "engagement": "Medium",
      "date": "2026-07-13T16:37:33.647Z",
      "id": "mr-1783960653647-bg",
      "trackerId": "t-2"
    },
    {
      "platform": "tiktok",
      "url": "https://www.tiktok.com/share/status/local-99798",
      "author": "@siti_nurhaliza",
      "title": "Review jujur layanan Gojek Indonesia",
      "content": "Keren banget inovasi dari Gojek Indonesia, dapet promo melimpah akhir pekan ini. Adminnya ramah dan penanganannya super cepat! #puas #mantap",
      "sentiment": "positive",
      "sentimentScore": 0.47,
      "emotion": "Joy",
      "engagement": "High",
      "date": "2026-07-13T16:37:13.646Z",
      "id": "mr-1783960633646-bg",
      "trackerId": "t-1"
    },
    {
      "platform": "facebook",
      "url": "https://www.facebook.com/share/status/local-167598",
      "author": "@siti_nurhaliza",
      "title": "Diskusi seputar Gojek Indonesia",
      "content": "Ada yang punya pengalaman pakai Gojek Indonesia baru-baru ini? Pengen tau performanya buat penggunaan harian. #diskusi",
      "sentiment": "neutral",
      "sentimentScore": -0.15,
      "emotion": "Neutral",
      "engagement": "Medium",
      "date": "2026-07-13T16:36:53.645Z",
      "id": "mr-1783960613645-bg",
      "trackerId": "t-1"
    },
    {
      "platform": "tiktok",
      "url": "https://www.tiktok.com/share/status/local-750609",
      "author": "Dewi Lestari",
      "title": "Review jujur layanan Kopi Kenangan",
      "content": "Keren banget inovasi dari Kopi Kenangan, dapet promo melimpah akhir pekan ini. Adminnya ramah dan penanganannya super cepat! #puas #mantap",
      "sentiment": "positive",
      "sentimentScore": 0.57,
      "emotion": "Joy",
      "engagement": "High",
      "date": "2026-07-13T16:36:33.645Z",
      "id": "mr-1783960593645-bg",
      "trackerId": "t-3"
    },
    {
      "platform": "facebook",
      "url": "https://www.facebook.com/share/status/local-636739",
      "author": "@andreas_s",
      "title": "Pembaruan sistem Gojek Indonesia",
      "content": "Melihat update terbaru dari aplikasi Gojek Indonesia, sepertinya mereka merombak layout navigasi utamanya. #update",
      "sentiment": "neutral",
      "sentimentScore": -0.13,
      "emotion": "Neutral",
      "engagement": "Medium",
      "date": "2026-07-13T16:36:13.644Z",
      "id": "mr-1783960573644-bg",
      "trackerId": "t-1"
    },
    {
      "platform": "instagram",
      "url": "https://www.instagram.com/share/status/local-400133",
      "author": "@rizky_pratama",
      "title": "Pembaruan sistem Kopi Kenangan",
      "content": "Melihat update terbaru dari aplikasi Kopi Kenangan, sepertinya mereka merombak layout navigasi utamanya. #update",
      "sentiment": "neutral",
      "sentimentScore": 0.02,
      "emotion": "Neutral",
      "engagement": "Medium",
      "date": "2026-07-13T16:35:53.644Z",
      "id": "mr-1783960553644-bg",
      "trackerId": "t-3"
    },
    {
      "platform": "instagram",
      "url": "https://www.instagram.com/share/status/local-444245",
      "author": "Rina Wulandari",
      "title": "Review jujur layanan Kopi Kenangan",
      "content": "Keren banget inovasi dari Kopi Kenangan, dapet promo melimpah akhir pekan ini. Adminnya ramah dan penanganannya super cepat! #puas #mantap",
      "sentiment": "positive",
      "sentimentScore": 0.58,
      "emotion": "Joy",
      "engagement": "High",
      "date": "2026-07-13T16:35:33.642Z",
      "id": "mr-1783960533642-bg",
      "trackerId": "t-3"
    },
    {
      "platform": "instagram",
      "url": "https://www.instagram.com/share/status/local-900195",
      "author": "Ahmad Fauzi",
      "title": "Pembaruan sistem Gojek Indonesia",
      "content": "Melihat update terbaru dari aplikasi Gojek Indonesia, sepertinya mereka merombak layout navigasi utamanya. #update",
      "sentiment": "neutral",
      "sentimentScore": -0.01,
      "emotion": "Neutral",
      "engagement": "Medium",
      "date": "2026-07-13T16:35:13.641Z",
      "id": "mr-1783960513641-bg",
      "trackerId": "t-1"
    },
    {
      "platform": "tiktok",
      "url": "https://www.tiktok.com/share/status/local-272127",
      "author": "Rina Wulandari",
      "title": "Keluhan performa Kopi Kenangan",
      "content": "Kenapa ya Kopi Kenangan belakangan ini agak lelet kalau diakses jam sibuk? Sering dapet pesan error koneksi. #keluhan #kecewa",
      "sentiment": "negative",
      "sentimentScore": -0.65,
      "emotion": "Anger",
      "engagement": "Medium",
      "date": "2026-07-13T16:34:53.640Z",
      "id": "mr-1783960493640-bg",
      "trackerId": "t-3"
    },
    {
      "platform": "instagram",
      "url": "https://www.instagram.com/share/status/local-766069",
      "author": "Rina Wulandari",
      "title": "Keluhan performa Kopi Kenangan",
      "content": "Kenapa ya Kopi Kenangan belakangan ini agak lelet kalau diakses jam sibuk? Sering dapet pesan error koneksi. #keluhan #kecewa",
      "sentiment": "negative",
      "sentimentScore": -0.65,
      "emotion": "Anger",
      "engagement": "Medium",
      "date": "2026-07-13T16:34:33.640Z",
      "id": "mr-1783960473640-bg",
      "trackerId": "t-3"
    },
    {
      "platform": "whatsapp",
      "url": "https://www.whatsapp.com/share/status/local-648612",
      "author": "@andreas_s",
      "title": "Diskusi seputar Gojek Indonesia",
      "content": "Ada yang punya pengalaman pakai Gojek Indonesia baru-baru ini? Pengen tau performanya buat penggunaan harian. #diskusi",
      "sentiment": "neutral",
      "sentimentScore": 0,
      "emotion": "Neutral",
      "engagement": "High",
      "date": "2026-07-13T16:34:13.640Z",
      "id": "mr-1783960453640-bg",
      "trackerId": "t-1"
    },
    {
      "platform": "tiktok",
      "url": "https://www.tiktok.com/share/status/local-506030",
      "author": "@budi_santoso",
      "title": "Keluhan performa Kopi Kenangan",
      "content": "Kenapa ya Kopi Kenangan belakangan ini agak lelet kalau diakses jam sibuk? Sering dapet pesan error koneksi. #keluhan #kecewa",
      "sentiment": "negative",
      "sentimentScore": -0.5,
      "emotion": "Anger",
      "engagement": "Medium",
      "date": "2026-07-13T16:33:53.639Z",
      "id": "mr-1783960433639-bg",
      "trackerId": "t-3"
    },
    {
      "platform": "instagram",
      "url": "https://www.instagram.com/share/status/local-381352",
      "author": "Agus Setiawan",
      "title": "Review jujur layanan MediaTrend",
      "content": "Keren banget inovasi dari MediaTrend, dapet promo melimpah akhir pekan ini. Adminnya ramah dan penanganannya super cepat! #puas #mantap",
      "sentiment": "positive",
      "sentimentScore": 0.65,
      "emotion": "Joy",
      "engagement": "High",
      "date": "2026-07-13T16:33:33.640Z",
      "id": "mr-1783960413640-bg",
      "trackerId": "t-2"
    },
    {
      "platform": "tiktok",
      "url": "https://www.tiktok.com/share/status/local-884538",
      "author": "@budi_santoso",
      "title": "Keluhan performa Kopi Kenangan",
      "content": "Kenapa ya Kopi Kenangan belakangan ini agak lelet kalau diakses jam sibuk? Sering dapet pesan error koneksi. #keluhan #kecewa",
      "sentiment": "negative",
      "sentimentScore": -0.81,
      "emotion": "Anger",
      "engagement": "Medium",
      "date": "2026-07-13T16:33:13.637Z",
      "id": "mr-1783960393637-bg",
      "trackerId": "t-3"
    },
    {
      "platform": "instagram",
      "url": "https://www.instagram.com/share/status/local-201438",
      "author": "@siti_nurhaliza",
      "title": "Rekomendasi Kopi Kenangan terbaik",
      "content": "Sumpah ini Kopi Kenangan membantu banget buat produktivitas sehari-hari! Pelayanannya cepet dan praktis abis. Sangat direkomendasikan untuk semuanya! #rekomendasi #mantap",
      "sentiment": "positive",
      "sentimentScore": 0.64,
      "emotion": "Joy",
      "engagement": "Medium",
      "date": "2026-07-13T16:32:27.650Z",
      "id": "mr-1783960347650-bg",
      "trackerId": "t-3"
    },
    {
      "platform": "instagram",
      "url": "https://www.instagram.com/share/status/local-288706",
      "author": "Agus Setiawan",
      "title": "Rekomendasi Kopi Kenangan terbaik",
      "content": "Sumpah ini Kopi Kenangan membantu banget buat produktivitas sehari-hari! Pelayanannya cepet dan praktis abis. Sangat direkomendasikan untuk semuanya! #rekomendasi #mantap",
      "sentiment": "positive",
      "sentimentScore": 0.57,
      "emotion": "Joy",
      "engagement": "Medium",
      "date": "2026-07-13T16:32:07.635Z",
      "id": "mr-1783960327635-bg",
      "trackerId": "t-3"
    },
    {
      "platform": "tiktok",
      "url": "https://www.tiktok.com/share/status/local-56706",
      "author": "@andreas_s",
      "title": "Review jujur layanan MediaTrend",
      "content": "Keren banget inovasi dari MediaTrend, dapet promo melimpah akhir pekan ini. Adminnya ramah dan penanganannya super cepat! #puas #mantap",
      "sentiment": "positive",
      "sentimentScore": 0.51,
      "emotion": "Joy",
      "engagement": "Medium",
      "date": "2026-07-13T16:31:47.634Z",
      "id": "mr-1783960307634-bg",
      "trackerId": "t-2"
    },
    {
      "platform": "whatsapp",
      "url": "https://www.whatsapp.com/share/status/local-144750",
      "author": "@budi_santoso",
      "title": "Diskusi seputar Gojek Indonesia",
      "content": "Ada yang punya pengalaman pakai Gojek Indonesia baru-baru ini? Pengen tau performanya buat penggunaan harian. #diskusi",
      "sentiment": "neutral",
      "sentimentScore": 0.09,
      "emotion": "Neutral",
      "engagement": "Medium",
      "date": "2026-07-13T16:31:27.633Z",
      "id": "mr-1783960287633-bg",
      "trackerId": "t-1"
    },
    {
      "platform": "tiktok",
      "url": "https://www.tiktok.com/share/status/local-307718",
      "author": "Ahmad Fauzi",
      "title": "Pembaruan sistem MediaTrend",
      "content": "Melihat update terbaru dari aplikasi MediaTrend, sepertinya mereka merombak layout navigasi utamanya. #update",
      "sentiment": "neutral",
      "sentimentScore": -0.11,
      "emotion": "Neutral",
      "engagement": "High",
      "date": "2026-07-13T16:31:07.633Z",
      "id": "mr-1783960267633-bg",
      "trackerId": "t-2"
    },
    {
      "platform": "whatsapp",
      "url": "https://www.whatsapp.com/share/status/local-79355",
      "author": "Dewi Lestari",
      "title": "Diskusi seputar Gojek Indonesia",
      "content": "Ada yang punya pengalaman pakai Gojek Indonesia baru-baru ini? Pengen tau performanya buat penggunaan harian. #diskusi",
      "sentiment": "neutral",
      "sentimentScore": -0.12,
      "emotion": "Neutral",
      "engagement": "Medium",
      "date": "2026-07-13T16:30:47.633Z",
      "id": "mr-1783960247633-bg",
      "trackerId": "t-1"
    },
    {
      "platform": "facebook",
      "url": "https://www.facebook.com/share/status/local-274807",
      "author": "@andreas_s",
      "title": "Keluhan performa Gojek Indonesia",
      "content": "Kenapa ya Gojek Indonesia belakangan ini agak lelet kalau diakses jam sibuk? Sering dapet pesan error koneksi. #keluhan #kecewa",
      "sentiment": "negative",
      "sentimentScore": -0.77,
      "emotion": "Anger",
      "engagement": "Medium",
      "date": "2026-07-13T16:30:27.632Z",
      "id": "mr-1783960227632-bg",
      "trackerId": "t-1"
    },
    {
      "platform": "instagram",
      "url": "https://www.instagram.com/share/status/local-171281",
      "author": "@rizky_pratama",
      "title": "Keluhan performa MediaTrend",
      "content": "Kenapa ya MediaTrend belakangan ini agak lelet kalau diakses jam sibuk? Sering dapet pesan error koneksi. #keluhan #kecewa",
      "sentiment": "negative",
      "sentimentScore": -0.78,
      "emotion": "Anger",
      "engagement": "Medium",
      "date": "2026-07-13T16:30:07.631Z",
      "id": "mr-1783960207631-bg",
      "trackerId": "t-2"
    },
    {
      "platform": "instagram",
      "url": "https://www.instagram.com/share/status/local-176750",
      "author": "Rina Wulandari",
      "title": "Review jujur layanan Kopi Kenangan",
      "content": "Keren banget inovasi dari Kopi Kenangan, dapet promo melimpah akhir pekan ini. Adminnya ramah dan penanganannya super cepat! #puas #mantap",
      "sentiment": "positive",
      "sentimentScore": 0.82,
      "emotion": "Joy",
      "engagement": "Medium",
      "date": "2026-07-13T16:29:47.631Z",
      "id": "mr-1783960187631-bg",
      "trackerId": "t-3"
    },
    {
      "platform": "tiktok",
      "url": "https://www.tiktok.com/share/status/local-404992",
      "author": "Ahmad Fauzi",
      "title": "Ulasan kritis MediaTrend",
      "content": "Harganya makin naik tapi kualitas pelayanan MediaTrend terasa stagnan. Semoga tim mereka segera melakukan evaluasi menyeluruh. #kecewa",
      "sentiment": "negative",
      "sentimentScore": -0.73,
      "emotion": "Anger",
      "engagement": "High",
      "date": "2026-07-13T16:29:27.630Z",
      "id": "mr-1783960167630-bg",
      "trackerId": "t-2"
    },
    {
      "platform": "instagram",
      "url": "https://www.instagram.com/share/status/local-215990",
      "author": "Dewi Lestari",
      "title": "Diskusi seputar Kopi Kenangan",
      "content": "Ada yang punya pengalaman pakai Kopi Kenangan baru-baru ini? Pengen tau performanya buat penggunaan harian. #diskusi",
      "sentiment": "neutral",
      "sentimentScore": 0.14,
      "emotion": "Neutral",
      "engagement": "Medium",
      "date": "2026-07-13T16:29:07.629Z",
      "id": "mr-1783960147629-bg",
      "trackerId": "t-3"
    },
    {
      "platform": "instagram",
      "url": "https://www.instagram.com/share/status/local-137852",
      "author": "Agus Setiawan",
      "title": "Rekomendasi Gojek Indonesia terbaik",
      "content": "Sumpah ini Gojek Indonesia membantu banget buat produktivitas sehari-hari! Pelayanannya cepet dan praktis abis. Sangat direkomendasikan untuk semuanya! #rekomendasi #mantap",
      "sentiment": "positive",
      "sentimentScore": 0.55,
      "emotion": "Joy",
      "engagement": "High",
      "date": "2026-07-13T16:28:47.628Z",
      "id": "mr-1783960127628-bg",
      "trackerId": "t-1"
    },
    {
      "platform": "instagram",
      "url": "https://www.instagram.com/share/status/local-989244",
      "author": "Rina Wulandari",
      "title": "Review jujur layanan Kopi Kenangan",
      "content": "Keren banget inovasi dari Kopi Kenangan, dapet promo melimpah akhir pekan ini. Adminnya ramah dan penanganannya super cepat! #puas #mantap",
      "sentiment": "positive",
      "sentimentScore": 0.63,
      "emotion": "Joy",
      "engagement": "Medium",
      "date": "2026-07-13T16:28:27.628Z",
      "id": "mr-1783960107628-bg",
      "trackerId": "t-3"
    },
    {
      "platform": "instagram",
      "url": "https://www.instagram.com/share/status/local-536479",
      "author": "Ahmad Fauzi",
      "title": "Rekomendasi MediaTrend terbaik",
      "content": "Sumpah ini MediaTrend membantu banget buat produktivitas sehari-hari! Pelayanannya cepet dan praktis abis. Sangat direkomendasikan untuk semuanya! #rekomendasi #mantap",
      "sentiment": "positive",
      "sentimentScore": 0.73,
      "emotion": "Joy",
      "engagement": "Medium",
      "date": "2026-07-13T16:28:07.627Z",
      "id": "mr-1783960087627-bg",
      "trackerId": "t-2"
    },
    {
      "platform": "instagram",
      "url": "https://www.instagram.com/share/status/local-101568",
      "author": "Ahmad Fauzi",
      "title": "Pembaruan sistem Kopi Kenangan",
      "content": "Melihat update terbaru dari aplikasi Kopi Kenangan, sepertinya mereka merombak layout navigasi utamanya. #update",
      "sentiment": "neutral",
      "sentimentScore": 0.12,
      "emotion": "Neutral",
      "engagement": "Medium",
      "date": "2026-07-13T16:27:47.626Z",
      "id": "mr-1783960067626-bg",
      "trackerId": "t-3"
    },
    {
      "platform": "instagram",
      "url": "https://www.instagram.com/share/status/local-649580",
      "author": "@andreas_s",
      "title": "Diskusi seputar MediaTrend",
      "content": "Ada yang punya pengalaman pakai MediaTrend baru-baru ini? Pengen tau performanya buat penggunaan harian. #diskusi",
      "sentiment": "neutral",
      "sentimentScore": 0.06,
      "emotion": "Neutral",
      "engagement": "Medium",
      "date": "2026-07-13T16:27:27.625Z",
      "id": "mr-1783960047625-bg",
      "trackerId": "t-2"
    },
    {
      "platform": "whatsapp",
      "url": "https://www.whatsapp.com/share/status/local-378636",
      "author": "@siti_nurhaliza",
      "title": "Review jujur layanan Gojek Indonesia",
      "content": "Keren banget inovasi dari Gojek Indonesia, dapet promo melimpah akhir pekan ini. Adminnya ramah dan penanganannya super cepat! #puas #mantap",
      "sentiment": "positive",
      "sentimentScore": 0.84,
      "emotion": "Joy",
      "engagement": "Medium",
      "date": "2026-07-13T16:27:07.624Z",
      "id": "mr-1783960027623-bg",
      "trackerId": "t-1"
    },
    {
      "platform": "instagram",
      "url": "https://www.instagram.com/share/status/local-316435",
      "author": "@budi_santoso",
      "title": "Diskusi seputar Gojek Indonesia",
      "content": "Ada yang punya pengalaman pakai Gojek Indonesia baru-baru ini? Pengen tau performanya buat penggunaan harian. #diskusi",
      "sentiment": "neutral",
      "sentimentScore": 0.01,
      "emotion": "Neutral",
      "engagement": "High",
      "date": "2026-07-13T16:26:47.623Z",
      "id": "mr-1783960007623-bg",
      "trackerId": "t-1"
    },
    {
      "platform": "tiktok",
      "url": "https://www.tiktok.com/share/status/local-851436",
      "author": "Rina Wulandari",
      "title": "Rekomendasi MediaTrend terbaik",
      "content": "Sumpah ini MediaTrend membantu banget buat produktivitas sehari-hari! Pelayanannya cepet dan praktis abis. Sangat direkomendasikan untuk semuanya! #rekomendasi #mantap",
      "sentiment": "positive",
      "sentimentScore": 0.61,
      "emotion": "Joy",
      "engagement": "High",
      "date": "2026-07-13T16:26:27.621Z",
      "id": "mr-1783959987621-bg",
      "trackerId": "t-2"
    },
    {
      "platform": "facebook",
      "url": "https://www.facebook.com/share/status/local-697729",
      "author": "@rizky_pratama",
      "title": "Review jujur layanan Gojek Indonesia",
      "content": "Keren banget inovasi dari Gojek Indonesia, dapet promo melimpah akhir pekan ini. Adminnya ramah dan penanganannya super cepat! #puas #mantap",
      "sentiment": "positive",
      "sentimentScore": 0.76,
      "emotion": "Joy",
      "engagement": "High",
      "date": "2026-07-13T16:26:07.621Z",
      "id": "mr-1783959967621-bg",
      "trackerId": "t-1"
    },
    {
      "platform": "instagram",
      "url": "https://www.instagram.com/share/status/local-568845",
      "author": "Ahmad Fauzi",
      "title": "Review jujur layanan Gojek Indonesia",
      "content": "Keren banget inovasi dari Gojek Indonesia, dapet promo melimpah akhir pekan ini. Adminnya ramah dan penanganannya super cepat! #puas #mantap",
      "sentiment": "positive",
      "sentimentScore": 0.6,
      "emotion": "Joy",
      "engagement": "Medium",
      "date": "2026-07-13T16:25:47.621Z",
      "id": "mr-1783959947621-bg",
      "trackerId": "t-1"
    },
    {
      "platform": "tiktok",
      "url": "https://www.tiktok.com/share/status/local-173551",
      "author": "Dewi Lestari",
      "title": "Keluhan performa Kopi Kenangan",
      "content": "Kenapa ya Kopi Kenangan belakangan ini agak lelet kalau diakses jam sibuk? Sering dapet pesan error koneksi. #keluhan #kecewa",
      "sentiment": "negative",
      "sentimentScore": -0.6,
      "emotion": "Anger",
      "engagement": "Medium",
      "date": "2026-07-13T16:25:27.619Z",
      "id": "mr-1783959927619-bg",
      "trackerId": "t-3"
    },
    {
      "platform": "instagram",
      "url": "https://www.instagram.com/share/status/local-471872",
      "author": "@budi_santoso",
      "title": "Rekomendasi Kopi Kenangan terbaik",
      "content": "Sumpah ini Kopi Kenangan membantu banget buat produktivitas sehari-hari! Pelayanannya cepet dan praktis abis. Sangat direkomendasikan untuk semuanya! #rekomendasi #mantap",
      "sentiment": "positive",
      "sentimentScore": 0.72,
      "emotion": "Joy",
      "engagement": "High",
      "date": "2026-07-13T16:25:07.619Z",
      "id": "mr-1783959907619-bg",
      "trackerId": "t-3"
    },
    {
      "platform": "instagram",
      "url": "https://www.instagram.com/share/status/local-112992",
      "author": "@rizky_pratama",
      "title": "Pembaruan sistem Kopi Kenangan",
      "content": "Melihat update terbaru dari aplikasi Kopi Kenangan, sepertinya mereka merombak layout navigasi utamanya. #update",
      "sentiment": "neutral",
      "sentimentScore": 0.04,
      "emotion": "Neutral",
      "engagement": "High",
      "date": "2026-07-13T16:24:47.618Z",
      "id": "mr-1783959887618-bg",
      "trackerId": "t-3"
    },
    {
      "platform": "tiktok",
      "url": "https://www.tiktok.com/share/status/local-68778",
      "author": "Rina Wulandari",
      "title": "Ulasan kritis Gojek Indonesia",
      "content": "Harganya makin naik tapi kualitas pelayanan Gojek Indonesia terasa stagnan. Semoga tim mereka segera melakukan evaluasi menyeluruh. #kecewa",
      "sentiment": "negative",
      "sentimentScore": -0.74,
      "emotion": "Anger",
      "engagement": "High",
      "date": "2026-07-13T16:24:27.618Z",
      "id": "mr-1783959867618-bg",
      "trackerId": "t-1"
    },
    {
      "platform": "instagram",
      "url": "https://www.instagram.com/share/status/local-839858",
      "author": "@siti_nurhaliza",
      "title": "Rekomendasi Kopi Kenangan terbaik",
      "content": "Sumpah ini Kopi Kenangan membantu banget buat produktivitas sehari-hari! Pelayanannya cepet dan praktis abis. Sangat direkomendasikan untuk semuanya! #rekomendasi #mantap",
      "sentiment": "positive",
      "sentimentScore": 0.48,
      "emotion": "Joy",
      "engagement": "High",
      "date": "2026-07-13T16:24:07.617Z",
      "id": "mr-1783959847617-bg",
      "trackerId": "t-3"
    },
    {
      "platform": "whatsapp",
      "url": "https://www.whatsapp.com/share/status/local-628740",
      "author": "Dewi Lestari",
      "title": "Diskusi seputar Gojek Indonesia",
      "content": "Ada yang punya pengalaman pakai Gojek Indonesia baru-baru ini? Pengen tau performanya buat penggunaan harian. #diskusi",
      "sentiment": "neutral",
      "sentimentScore": -0.05,
      "emotion": "Neutral",
      "engagement": "Medium",
      "date": "2026-07-13T16:23:47.616Z",
      "id": "mr-1783959827616-bg",
      "trackerId": "t-1"
    },
    {
      "platform": "instagram",
      "url": "https://www.instagram.com/share/status/local-932140",
      "author": "Ahmad Fauzi",
      "title": "Diskusi seputar Kopi Kenangan",
      "content": "Ada yang punya pengalaman pakai Kopi Kenangan baru-baru ini? Pengen tau performanya buat penggunaan harian. #diskusi",
      "sentiment": "neutral",
      "sentimentScore": 0.1,
      "emotion": "Neutral",
      "engagement": "Medium",
      "date": "2026-07-13T16:23:27.615Z",
      "id": "mr-1783959807615-bg",
      "trackerId": "t-3"
    },
    {
      "platform": "instagram",
      "url": "https://www.instagram.com/share/status/local-198206",
      "author": "Dewi Lestari",
      "title": "Review jujur layanan Gojek Indonesia",
      "content": "Keren banget inovasi dari Gojek Indonesia, dapet promo melimpah akhir pekan ini. Adminnya ramah dan penanganannya super cepat! #puas #mantap",
      "sentiment": "positive",
      "sentimentScore": 0.63,
      "emotion": "Joy",
      "engagement": "Medium",
      "date": "2026-07-13T16:23:07.614Z",
      "id": "mr-1783959787614-bg",
      "trackerId": "t-1"
    },
    {
      "platform": "tiktok",
      "url": "https://www.tiktok.com/share/status/local-301972",
      "author": "Dewi Lestari",
      "title": "Review jujur layanan Kopi Kenangan",
      "content": "Keren banget inovasi dari Kopi Kenangan, dapet promo melimpah akhir pekan ini. Adminnya ramah dan penanganannya super cepat! #puas #mantap",
      "sentiment": "positive",
      "sentimentScore": 0.65,
      "emotion": "Joy",
      "engagement": "High",
      "date": "2026-07-13T16:22:47.613Z",
      "id": "mr-1783959767613-bg",
      "trackerId": "t-3"
    },
    {
      "platform": "instagram",
      "url": "https://www.instagram.com/share/status/local-483985",
      "author": "@rizky_pratama",
      "title": "Rekomendasi MediaTrend terbaik",
      "content": "Sumpah ini MediaTrend membantu banget buat produktivitas sehari-hari! Pelayanannya cepet dan praktis abis. Sangat direkomendasikan untuk semuanya! #rekomendasi #mantap",
      "sentiment": "positive",
      "sentimentScore": 0.82,
      "emotion": "Joy",
      "engagement": "High",
      "date": "2026-07-13T16:22:21.294Z",
      "id": "mr-1783959741294-bg",
      "trackerId": "t-2"
    },
    {
      "platform": "tiktok",
      "url": "https://www.tiktok.com/share/status/local-142629",
      "author": "Rina Wulandari",
      "title": "Diskusi seputar Kopi Kenangan",
      "content": "Ada yang punya pengalaman pakai Kopi Kenangan baru-baru ini? Pengen tau performanya buat penggunaan harian. #diskusi",
      "sentiment": "neutral",
      "sentimentScore": 0.06,
      "emotion": "Neutral",
      "engagement": "Medium",
      "date": "2026-07-13T16:22:01.294Z",
      "id": "mr-1783959721294-bg",
      "trackerId": "t-3"
    },
    {
      "platform": "whatsapp",
      "url": "https://www.whatsapp.com/share/status/local-536348",
      "author": "@siti_nurhaliza",
      "title": "Review jujur layanan Gojek Indonesia",
      "content": "Keren banget inovasi dari Gojek Indonesia, dapet promo melimpah akhir pekan ini. Adminnya ramah dan penanganannya super cepat! #puas #mantap",
      "sentiment": "positive",
      "sentimentScore": 0.43,
      "emotion": "Joy",
      "engagement": "High",
      "date": "2026-07-13T16:21:41.293Z",
      "id": "mr-1783959701293-bg",
      "trackerId": "t-1"
    },
    {
      "platform": "tiktok",
      "url": "https://www.tiktok.com/share/status/local-272140",
      "author": "@budi_santoso",
      "title": "Keluhan performa Kopi Kenangan",
      "content": "Kenapa ya Kopi Kenangan belakangan ini agak lelet kalau diakses jam sibuk? Sering dapet pesan error koneksi. #keluhan #kecewa",
      "sentiment": "negative",
      "sentimentScore": -0.77,
      "emotion": "Anger",
      "engagement": "High",
      "date": "2026-07-13T16:21:21.293Z",
      "id": "mr-1783959681293-bg",
      "trackerId": "t-3"
    },
    {
      "platform": "instagram",
      "url": "https://www.instagram.com/share/status/local-133213",
      "author": "@budi_santoso",
      "title": "Review jujur layanan MediaTrend",
      "content": "Keren banget inovasi dari MediaTrend, dapet promo melimpah akhir pekan ini. Adminnya ramah dan penanganannya super cepat! #puas #mantap",
      "sentiment": "positive",
      "sentimentScore": 0.41,
      "emotion": "Joy",
      "engagement": "Medium",
      "date": "2026-07-13T16:21:01.292Z",
      "id": "mr-1783959661292-bg",
      "trackerId": "t-2"
    },
    {
      "platform": "instagram",
      "url": "https://www.instagram.com/share/status/local-243583",
      "author": "Ahmad Fauzi",
      "title": "Ulasan kritis MediaTrend",
      "content": "Harganya makin naik tapi kualitas pelayanan MediaTrend terasa stagnan. Semoga tim mereka segera melakukan evaluasi menyeluruh. #kecewa",
      "sentiment": "negative",
      "sentimentScore": -0.63,
      "emotion": "Anger",
      "engagement": "Medium",
      "date": "2026-07-13T16:20:41.292Z",
      "id": "mr-1783959641292-bg",
      "trackerId": "t-2"
    },
    {
      "platform": "instagram",
      "url": "https://www.instagram.com/share/status/local-332436",
      "author": "Rina Wulandari",
      "title": "Rekomendasi Kopi Kenangan terbaik",
      "content": "Sumpah ini Kopi Kenangan membantu banget buat produktivitas sehari-hari! Pelayanannya cepet dan praktis abis. Sangat direkomendasikan untuk semuanya! #rekomendasi #mantap",
      "sentiment": "positive",
      "sentimentScore": 0.73,
      "emotion": "Joy",
      "engagement": "High",
      "date": "2026-07-13T16:20:21.289Z",
      "id": "mr-1783959621289-bg",
      "trackerId": "t-3"
    },
    {
      "platform": "instagram",
      "url": "https://www.instagram.com/share/status/local-905051",
      "author": "@rizky_pratama",
      "title": "Pembaruan sistem MediaTrend",
      "content": "Melihat update terbaru dari aplikasi MediaTrend, sepertinya mereka merombak layout navigasi utamanya. #update",
      "sentiment": "neutral",
      "sentimentScore": -0.07,
      "emotion": "Neutral",
      "engagement": "Medium",
      "date": "2026-07-13T16:20:01.287Z",
      "id": "mr-1783959601287-bg",
      "trackerId": "t-2"
    },
    {
      "platform": "instagram",
      "url": "https://www.instagram.com/share/status/local-909167",
      "author": "@budi_santoso",
      "title": "Keluhan performa MediaTrend",
      "content": "Kenapa ya MediaTrend belakangan ini agak lelet kalau diakses jam sibuk? Sering dapet pesan error koneksi. #keluhan #kecewa",
      "sentiment": "negative",
      "sentimentScore": -0.58,
      "emotion": "Anger",
      "engagement": "High",
      "date": "2026-07-13T16:19:41.287Z",
      "id": "mr-1783959581287-bg",
      "trackerId": "t-2"
    },
    {
      "platform": "tiktok",
      "url": "https://www.tiktok.com/share/status/local-422554",
      "author": "@rizky_pratama",
      "title": "Diskusi seputar Gojek Indonesia",
      "content": "Ada yang punya pengalaman pakai Gojek Indonesia baru-baru ini? Pengen tau performanya buat penggunaan harian. #diskusi",
      "sentiment": "neutral",
      "sentimentScore": 0.06,
      "emotion": "Neutral",
      "engagement": "Medium",
      "date": "2026-07-13T16:19:21.287Z",
      "id": "mr-1783959561287-bg",
      "trackerId": "t-1"
    },
    {
      "platform": "instagram",
      "url": "https://www.instagram.com/share/status/local-965469",
      "author": "@rizky_pratama",
      "title": "Ulasan kritis Gojek Indonesia",
      "content": "Harganya makin naik tapi kualitas pelayanan Gojek Indonesia terasa stagnan. Semoga tim mereka segera melakukan evaluasi menyeluruh. #kecewa",
      "sentiment": "negative",
      "sentimentScore": -0.52,
      "emotion": "Anger",
      "engagement": "High",
      "date": "2026-07-13T16:19:01.286Z",
      "id": "mr-1783959541286-bg",
      "trackerId": "t-1"
    },
    {
      "platform": "tiktok",
      "url": "https://www.tiktok.com/share/status/local-175489",
      "author": "Rina Wulandari",
      "title": "Rekomendasi Gojek Indonesia terbaik",
      "content": "Sumpah ini Gojek Indonesia membantu banget buat produktivitas sehari-hari! Pelayanannya cepet dan praktis abis. Sangat direkomendasikan untuk semuanya! #rekomendasi #mantap",
      "sentiment": "positive",
      "sentimentScore": 0.55,
      "emotion": "Joy",
      "engagement": "High",
      "date": "2026-07-13T16:18:41.285Z",
      "id": "mr-1783959521285-bg",
      "trackerId": "t-1"
    },
    {
      "platform": "whatsapp",
      "url": "https://www.whatsapp.com/share/status/local-369820",
      "author": "@rizky_pratama",
      "title": "Rekomendasi Gojek Indonesia terbaik",
      "content": "Sumpah ini Gojek Indonesia membantu banget buat produktivitas sehari-hari! Pelayanannya cepet dan praktis abis. Sangat direkomendasikan untuk semuanya! #rekomendasi #mantap",
      "sentiment": "positive",
      "sentimentScore": 0.47,
      "emotion": "Joy",
      "engagement": "Medium",
      "date": "2026-07-13T16:18:21.285Z",
      "id": "mr-1783959501285-bg",
      "trackerId": "t-1"
    },
    {
      "platform": "tiktok",
      "url": "https://www.tiktok.com/share/status/local-904925",
      "author": "@siti_nurhaliza",
      "title": "Review jujur layanan MediaTrend",
      "content": "Keren banget inovasi dari MediaTrend, dapet promo melimpah akhir pekan ini. Adminnya ramah dan penanganannya super cepat! #puas #mantap",
      "sentiment": "positive",
      "sentimentScore": 0.84,
      "emotion": "Joy",
      "engagement": "High",
      "date": "2026-07-13T16:18:01.285Z",
      "id": "mr-1783959481285-bg",
      "trackerId": "t-2"
    }
  ]
}